qp_flexzboost/__init__.py
qp_flexzboost/_version.py
qp_flexzboost/flexzboost_pdf.py
qp_flexzboost-1.0.2.dist-info/licenses/LICENSE
qp_flexzboost-1.0.2.dist-info/METADATA
qp_flexzboost-1.0.2.dist-info/WHEEL
qp_flexzboost-1.0.2.dist-info/top_level.txt
qp_flexzboost-1.0.2.dist-info/RECORD
