Metadata-Version: 2.4
Name: qp_flexzboost
Version: 1.0.2
Author-email: LINCC Frameworks <lincc-frameworks-team@lists.lsst.org>, Drew Oldag <awoldag@uw.edu>
License: MIT License
Classifier: Development Status :: 4 - Beta
Classifier: License :: OSI Approved :: MIT License
Classifier: Intended Audience :: Developers
Classifier: Intended Audience :: Science/Research
Classifier: Operating System :: OS Independent
Classifier: Programming Language :: Python :: 3
Classifier: Topic :: Scientific/Engineering :: Astronomy
License-File: LICENSE
Requires-Dist: flexcode
Requires-Dist: numpy>=1.24
Requires-Dist: qp-prob>=1.0.0
Requires-Dist: scipy>=1.9.0
Provides-Extra: dev
Requires-Dist: ipykernel; extra == "dev"
Requires-Dist: pytest; extra == "dev"
Requires-Dist: pytest-cov; extra == "dev"
Requires-Dist: pre-commit; extra == "dev"
Requires-Dist: qp-prob[full]>=1.0.0; extra == "dev"
Requires-Dist: sphinx==6.1.3; extra == "dev"
Requires-Dist: sphinx-rtd-theme==1.2.0; extra == "dev"
Requires-Dist: sphinx-autoapi==2.0.1; extra == "dev"
Requires-Dist: black; extra == "dev"
Requires-Dist: nbconvert; extra == "dev"
Requires-Dist: nbsphinx; extra == "dev"
Requires-Dist: ipython; extra == "dev"
Requires-Dist: matplotlib; extra == "dev"
Requires-Dist: jupyter; extra == "dev"
Requires-Dist: jupytext; extra == "dev"
Dynamic: license-file
